xanadu_sphinx_theme/__init__.py
xanadu_sphinx_theme/_version.py
xanadu_sphinx_theme/footer.html
xanadu_sphinx_theme/globaltoc.html
xanadu_sphinx_theme/header.html
xanadu_sphinx_theme/layout.html
xanadu_sphinx_theme/localtoc.html
xanadu_sphinx_theme/search.html
xanadu_sphinx_theme/searchbox.html
xanadu_sphinx_theme/theme.conf
xanadu_sphinx_theme/directives/__init__.py
xanadu_sphinx_theme/directives/bio.py
xanadu_sphinx_theme/directives/community_card.py
xanadu_sphinx_theme/directives/details.py
xanadu_sphinx_theme/directives/gallery_item.py
xanadu_sphinx_theme/directives/index_card.py
xanadu_sphinx_theme/directives/related_demo.py
xanadu_sphinx_theme/directives/title_card.py
xanadu_sphinx_theme/directives/youtube_video.py
xanadu_sphinx_theme/static/xanadu.css_t
xanadu_sphinx_theme/static/xanadu_logo.svg_t
xanadu_sphinx_theme/templates/autosummary/base.rst
xanadu_sphinx_theme/templates/autosummary/class.rst
xanadu_sphinx_theme/templates/autosummary/module.rst
xanadu_sphinx_theme/templates/autosummary_core/base.rst
xanadu_sphinx_theme/templates/autosummary_core/class.rst
xanadu_sphinx_theme/templates/autosummary_core/module.rst
xanadu_sphinx_theme-0.17.0.dist-info/licenses/LICENSE
xanadu_sphinx_theme-0.17.0.dist-info/METADATA
xanadu_sphinx_theme-0.17.0.dist-info/WHEEL
xanadu_sphinx_theme-0.17.0.dist-info/entry_points.txt
xanadu_sphinx_theme-0.17.0.dist-info/top_level.txt
xanadu_sphinx_theme-0.17.0.dist-info/RECORD
